{
  "input": {
    "PanelType": "安装板",
    "PanelSize": [
      800.0,
      1200.0
    ],
    "Parts": [
      {
        "ID": "6EED1",
        "Type": "双电源自动转换开关",
        "Size": [
          266.0,
          192.0
        ]
      },
      {
        "ID": "6EECF",
        "Type": "塑壳断路器",
        "Size": [
          92.0,
          150.0
        ]
      },
      {
        "ID": "6EECE",
        "Type": "塑壳断路器",
        "Size": [
          92.0,
          150.0
        ]
      },
      {
        "ID": "6EECD",
        "Type": "塑壳断路器",
        "Size": [
          92.0,
          150.0
        ]
      },
      {
        "ID": "6EECC",
        "Type": "微型断路器",
        "Size": [
          54.0,
          83.0
        ]
      },
      {
        "ID": "6EECB",
        "Type": "微型断路器",
        "Size": [
          54.0,
          83.0
        ]
      },
      {
        "ID": "6EECA",
        "Type": "电能表",
        "Size": [
          144.0,
          105.07633132400224
        ]
      },
      {
        "ID": "6EEC9",
        "Type": "电能表",
        "Size": [
          144.0,
          105.07633132400224
        ]
      },
      {
        "ID": "6EEC8",
        "Type": "电能表",
        "Size": [
          144.0,
          105.07633132400224
        ]
      },
      {
        "ID": "6EEC7",
        "Type": "电能表",
        "Size": [
          144.0,
          105.07633132400224
        ]
      },
      {
        "ID": "6EEC6",
        "Type": "塑壳断路器",
        "Size": [
          92.0,
          150.0
        ]
      },
      {
        "ID": "6EEC5",
        "Type": "塑壳断路器",
        "Size": [
          92.0,
          150.0
        ]
      },
      {
        "ID": "6EEC4",
        "Type": "微型断路器",
        "Size": [
          72.0,
          83.0
        ]
      },
      {
        "ID": "6EEC3",
        "Type": "浪涌保护器",
        "Size": [
          72.00000021792948,
          78.99999618530273
        ]
      },
      {
        "ID": "6EEC2",
        "Type": "电能表",
        "Size": [
          144.0,
          105.07633132400224
        ]
      }
    ]
  },
  "output": [
    {
      "ID": "6EED1",
      "Pos": [
        75.73462439049035,
        357.0
      ]
    },
    {
      "ID": "6EECF",
      "Pos": [
        306.35571589134634,
        776.0711306524463
      ]
    },
    {
      "ID": "6EECE",
      "Pos": [
        408.35571589134634,
        776.0711306524463
      ]
    },
    {
      "ID": "6EECD",
      "Pos": [
        510.35571589134634,
        776.0711306524463
      ]
    },
    {
      "ID": "6EECC",
      "Pos": [
        148.47224644804373,
        200.88410769973416
      ]
    },
    {
      "ID": "6EECB",
      "Pos": [
        236.4490933981724,
        200.88410769973416
      ]
    },
    {
      "ID": "6EECA",
      "Pos": [
        452.9687350327149,
        151.2198138757958
      ]
    },
    {
      "ID": "6EEC9",
      "Pos": [
        596.9687350327149,
        151.2198138757958
      ]
    },
    {
      "ID": "6EEC8",
      "Pos": [
        452.9687350327149,
        357.2198138757958
      ]
    },
    {
      "ID": "6EEC7",
      "Pos": [
        596.9687350327149,
        357.2198138757958
      ]
    },
    {
      "ID": "6EEC6",
      "Pos": [
        94.49596272595227,
        780.8395739010302
      ]
    },
    {
      "ID": "6EEC5",
      "Pos": [
        196.49596272595227,
        780.8395739010302
      ]
    },
    {
      "ID": "6EEC4",
      "Pos": [
        627.4501258218661,
        805.7698790736031
      ]
    },
    {
      "ID": "6EEC3",
      "Pos": [
        632.7858661995269,
        980.50421936973
      ]
    },
    {
      "ID": "6EEC2",
      "Pos": [
        596.9687350327149,
        564.5570336172241
      ]
    }
  ]
}