{
  "input": {
    "CabType": "配电箱",
    "PanelType": "安装板",
    "Size": [
      600.0,
      2200.0
    ],
    "Parts": [
      {
        "ID": "13573E",
        "Type": "UK-2.5 5组",
        "Size": [
          25.0,
          43.0
        ]
      },
      {
        "ID": "13573D",
        "Type": "UK-2.5 5组",
        "Size": [
          25.0,
          43.0
        ]
      },
      {
        "ID": "13573C",
        "Type": "端子堵头",
        "Size": [
          9.0,
          42.0
        ]
      },
      {
        "ID": "13573B",
        "Type": "UK-2.5 5组",
        "Size": [
          25.0,
          43.0
        ]
      },
      {
        "ID": "13573A",
        "Type": "UK-2.5 5组",
        "Size": [
          25.0,
          43.0
        ]
      },
      {
        "ID": "135739",
        "Type": "端子堵头",
        "Size": [
          9.0,
          42.0
        ]
      },
      {
        "ID": "135738",
        "Type": "A$C182C2388",
        "Size": [
          130.20731258229353,
          90.0
        ]
      },
      {
        "ID": "135737",
        "Type": "HH54P",
        "Size": [
          30.0,
          71.0
        ]
      },
      {
        "ID": "135736",
        "Type": "HH52P",
        "Size": [
          21.995882438030094,
          71.0
        ]
      },
      {
        "ID": "135735",
        "Type": "HH52P",
        "Size": [
          21.995882437797263,
          71.0
        ]
      },
      {
        "ID": "135734",
        "Type": "HH54P",
        "Size": [
          30.0,
          71.0
        ]
      },
      {
        "ID": "135733",
        "Type": "HH54P",
        "Size": [
          30.0,
          71.0
        ]
      },
      {
        "ID": "135732",
        "Type": "RT18-32X-6A",
        "Size": [
          18.0,
          82.0
        ]
      },
      {
        "ID": "135731",
        "Type": "RT18-32X-6A",
        "Size": [
          18.0,
          82.0
        ]
      },
      {
        "ID": "135730",
        "Type": "端子堵头",
        "Size": [
          9.0,
          42.0
        ]
      },
      {
        "ID": "13572F",
        "Type": "KB0-MSCPS-45上海勉速-2024.1",
        "Size": [
          93.0,
          249.0
        ]
      },
      {
        "ID": "13572E",
        "Type": "A$C182C2388",
        "Size": [
          130.20731258229353,
          90.0
        ]
      },
      {
        "ID": "13572D",
        "Type": "HH54P",
        "Size": [
          30.0,
          71.0
        ]
      },
      {
        "ID": "13572C",
        "Type": "端子堵头",
        "Size": [
          9.0,
          42.0
        ]
      },
      {
        "ID": "13572B",
        "Type": "HH52P",
        "Size": [
          21.995882438030094,
          71.0
        ]
      },
      {
        "ID": "13572A",
        "Type": "HH52P",
        "Size": [
          21.995882437797263,
          71.0
        ]
      },
      {
        "ID": "135729",
        "Type": "HH54P",
        "Size": [
          30.0,
          71.0
        ]
      },
      {
        "ID": "135728",
        "Type": "HH54P",
        "Size": [
          30.0,
          71.0
        ]
      },
      {
        "ID": "135727",
        "Type": "端子50B-2x35 1只",
        "Size": [
          43.0,
          149.01245176547673
        ]
      },
      {
        "ID": "135726",
        "Type": "微端3P-54mm-2022.1",
        "Size": [
          54.0,
          135.0
        ]
      },
      {
        "ID": "135725",
        "Type": "端子50B-2x35 1只",
        "Size": [
          43.0,
          149.01245176541852
        ]
      },
      {
        "ID": "135724",
        "Type": "TC100A 3P",
        "Size": [
          105.0,
          55.0
        ]
      },
      {
        "ID": "135723",
        "Type": "A$C426090bb",
        "Size": [
          108.0,
          82.0
        ]
      },
      {
        "ID": "135722",
        "Type": "A$C63FD753C",
        "Size": [
          33.0,
          43.0
        ]
      },
      {
        "ID": "135721",
        "Type": "A$C1DDE3F93",
        "Size": [
          126.0,
          82.0
        ]
      },
      {
        "ID": "135720",
        "Type": "A$C03D07FCC",
        "Size": [
          24.0,
          43.0
        ]
      },
      {
        "ID": "13571F",
        "Type": "ED系列导轨表-海恩德",
        "Size": [
          71.5,
          90.0
        ]
      },
      {
        "ID": "13571E",
        "Type": "HH54P",
        "Size": [
          30.0,
          71.0
        ]
      },
      {
        "ID": "13571D",
        "Type": "UK-2.5 5组",
        "Size": [
          25.0,
          43.0
        ]
      },
      {
        "ID": "13571C",
        "Type": "UK-2.5 5组",
        "Size": [
          25.0,
          43.0
        ]
      },
      {
        "ID": "13571B",
        "Type": "端子堵头",
        "Size": [
          9.0,
          42.0
        ]
      },
      {
        "ID": "13571A",
        "Type": "UK-2.5 5组",
        "Size": [
          25.0,
          43.0
        ]
      },
      {
        "ID": "135719",
        "Type": "UK-2.5 5组",
        "Size": [
          25.0,
          43.0
        ]
      },
      {
        "ID": "135718",
        "Type": "端子堵头",
        "Size": [
          9.0,
          42.0
        ]
      },
      {
        "ID": "135717",
        "Type": "端子堵头",
        "Size": [
          9.0,
          42.0
        ]
      },
      {
        "ID": "135716",
        "Type": "端子堵头",
        "Size": [
          9.0,
          42.0
        ]
      },
      {
        "ID": "135715",
        "Type": "RT18-32X-6A",
        "Size": [
          18.0,
          82.0
        ]
      },
      {
        "ID": "135714",
        "Type": "HH52P",
        "Size": [
          21.995882437797263,
          71.0
        ]
      },
      {
        "ID": "135713",
        "Type": "HH52P",
        "Size": [
          21.995882438030094,
          71.0
        ]
      },
      {
        "ID": "135712",
        "Type": "HH54P",
        "Size": [
          30.0,
          71.0
        ]
      },
      {
        "ID": "135711",
        "Type": "HH54P",
        "Size": [
          30.0,
          71.0
        ]
      },
      {
        "ID": "135710",
        "Type": "UK-2.5 5组",
        "Size": [
          25.0,
          43.0
        ]
      },
      {
        "ID": "13570F",
        "Type": "UK-2.5 5组",
        "Size": [
          25.0,
          43.0
        ]
      },
      {
        "ID": "13570E",
        "Type": "端子堵头",
        "Size": [
          9.0,
          42.0
        ]
      },
      {
        "ID": "13570D",
        "Type": "UK-2.5 5组",
        "Size": [
          25.0,
          43.0
        ]
      },
      {
        "ID": "13570C",
        "Type": "UK-2.5 5组",
        "Size": [
          25.0,
          43.0
        ]
      },
      {
        "ID": "13570B",
        "Type": "端子堵头",
        "Size": [
          9.0,
          42.0
        ]
      },
      {
        "ID": "13570A",
        "Type": "双电源TBBQ31-160A-4P-2022.3",
        "Size": [
          285.0,
          272.0
        ]
      },
      {
        "ID": "135709",
        "Type": "浪涌保护器 72mm-2022.1",
        "Size": [
          72.0,
          135.0
        ]
      },
      {
        "ID": "135708",
        "Type": "KB0-MSCPS-45上海勉速-2024.1",
        "Size": [
          93.0,
          249.0
        ]
      },
      {
        "ID": "135707",
        "Type": "KB0-MSCPS-45上海勉速-2024.1",
        "Size": [
          93.0,
          249.0
        ]
      },
      {
        "ID": "135706",
        "Type": "微端3P-54mm-2022.1",
        "Size": [
          54.0,
          135.0
        ]
      },
      {
        "ID": "135705",
        "Type": "微端3P-54mm-2022.1",
        "Size": [
          54.0,
          135.0
        ]
      },
      {
        "ID": "135704",
        "Type": "微端3P-54mm-2022.1",
        "Size": [
          54.0,
          135.0
        ]
      },
      {
        "ID": "135703",
        "Type": "微端3P-54mm-2022.1",
        "Size": [
          54.0,
          135.0
        ]
      },
      {
        "ID": "135702",
        "Type": "微端1P-18mm-2022.1",
        "Size": [
          18.0,
          135.0
        ]
      },
      {
        "ID": "135701",
        "Type": "后备保护-72mm-2022.1",
        "Size": [
          82.10692774457857,
          134.0
        ]
      },
      {
        "ID": "135700",
        "Type": "JBF62P-ATV2",
        "Size": [
          110.0,
          94.5
        ]
      },
      {
        "ID": "1356A3",
        "Type": "*U800",
        "Size": [
          9.0,
          1989.0
        ]
      },
      {
        "ID": "1356A1",
        "Type": "A$C7A207737",
        "Size": [
          530.000004499685,
          176.32938821963035
        ]
      },
      {
        "ID": "1356A0",
        "Type": "*U785",
        "Size": [
          9.0,
          1989.0
        ]
      },
      {
        "ID": "13569A",
        "Type": "911",
        "Size": [
          267.38641871442087,
          27.719999998400453
        ]
      },
      {
        "ID": "135698",
        "Type": "A$C11EF57A1",
        "Size": [
          14.0,
          20.0
        ]
      }
    ]
  },
  "output": [
    {
      "ID": "13573E",
      "Pos": [
        496.76686550909653,
        1303.0000312443008
      ]
    },
    {
      "ID": "13573D",
      "Pos": [
        446.76686550909653,
        1303.0000312443008
      ]
    },
    {
      "ID": "13573C",
      "Pos": [
        521.7668655088637,
        1303.500031244359
      ]
    },
    {
      "ID": "13573B",
      "Pos": [
        471.76686550909653,
        1303.0000312443008
      ]
    },
    {
      "ID": "13573A",
      "Pos": [
        421.76686550909653,
        1303.0000312443008
      ]
    },
    {
      "ID": "135739",
      "Pos": [
        412.7668655088637,
        1303.500031244359
      ]
    },
    {
      "ID": "135738",
      "Pos": [
        354.90377069730312,
        1455.0000312443008
      ]
    },
    {
      "ID": "135737",
      "Pos": [
        373.26686550909653,
        1289.0000312443008
      ]
    },
    {
      "ID": "135736",
      "Pos": [
        268.77510063513182,
        1289.0000312443008
      ]
    },
    {
      "ID": "135735",
      "Pos": [
        290.77098307292908,
        1289.0000312443008
      ]
    },
    {
      "ID": "135734",
      "Pos": [
        343.26686550909653,
        1289.0000312443008
      ]
    },
    {
      "ID": "135733",
      "Pos": [
        312.76686551095918,
        1289.0000312443008
      ]
    },
    {
      "ID": "135732",
      "Pos": [
        116.28333576116711,
        1284.5000312443008
      ]
    },
    {
      "ID": "135731",
      "Pos": [
        98.283335761167109,
        1284.5000312443008
      ]
    },
    {
      "ID": "135730",
      "Pos": [
        215.90377069730312,
        1479.0000312443008
      ]
    },
    {
      "ID": "13572F",
      "Pos": [
        435.0329479414504,
        940.00003124424256
      ]
    },
    {
      "ID": "13572E",
      "Pos": [
        224.90377069730312,
        1455.0000312443008
      ]
    },
    {
      "ID": "13572D",
      "Pos": [
        185.90377069730312,
        1464.5000312443008
      ]
    },
    {
      "ID": "13572C",
      "Pos": [
        403.7668655088637,
        1303.500031244359
      ]
    },
    {
      "ID": "13572B",
      "Pos": [
        81.4120058233384,
        1464.5000312443008
      ]
    },
    {
      "ID": "13572A",
      "Pos": [
        103.40788826113567,
        1464.5000312443008
      ]
    },
    {
      "ID": "135729",
      "Pos": [
        155.90377069730312,
        1464.5000312443008
      ]
    },
    {
      "ID": "135728",
      "Pos": [
        125.40377069916576,
        1464.5000312443008
      ]
    },
    {
      "ID": "135727",
      "Pos": [
        450.74521886650473,
        167.98757947864942
      ]
    },
    {
      "ID": "135726",
      "Pos": [
        396.74521886650473,
        180.00003124418436
      ]
    },
    {
      "ID": "135725",
      "Pos": [
        353.74521886650473,
        167.98757947876584
      ]
    },
    {
      "ID": "135724",
      "Pos": [
        416.22093362780288,
        759.50003124424256
      ]
    },
    {
      "ID": "135723",
      "Pos": [
        191.74521886650473,
        207.50003124424256
      ]
    },
    {
      "ID": "135722",
      "Pos": [
        172.28333576116711,
        780.50003124430077
      ]
    },
    {
      "ID": "135721",
      "Pos": [
        83.745218866504729,
        207.50003124424256
      ]
    },
    {
      "ID": "135720",
      "Pos": [
        504.47093362780288,
        573.00003124424256
      ]
    },
    {
      "ID": "13571F",
      "Pos": [
        432.97093362780288,
        549.50003124424256
      ]
    },
    {
      "ID": "13571E",
      "Pos": [
        238.77510063513182,
        1289.0000312443008
      ]
    },
    {
      "ID": "13571D",
      "Pos": [
        164.30022971215658,
        956.05201522499556
      ]
    },
    {
      "ID": "13571C",
      "Pos": [
        114.30022971215658,
        956.05201522499556
      ]
    },
    {
      "ID": "13571B",
      "Pos": [
        189.30022971192375,
        956.55201522505376
      ]
    },
    {
      "ID": "13571A",
      "Pos": [
        139.30022971215658,
        956.05201522499556
      ]
    },
    {
      "ID": "135719",
      "Pos": [
        89.300229712156579,
        956.05201522499556
      ]
    },
    {
      "ID": "135718",
      "Pos": [
        80.300229711923748,
        956.55201522505376
      ]
    },
    {
      "ID": "135717",
      "Pos": [
        72.4120058233384,
        1479.0000312443008
      ]
    },
    {
      "ID": "135716",
      "Pos": [
        71.283335761167109,
        1303.5000312443008
      ]
    },
    {
      "ID": "135715",
      "Pos": [
        80.283335761167109,
        1284.5000312442426
      ]
    },
    {
      "ID": "135714",
      "Pos": [
        134.28333576116711,
        1289.0000312443008
      ]
    },
    {
      "ID": "135713",
      "Pos": [
        156.27921819896437,
        1289.0000312443008
      ]
    },
    {
      "ID": "135712",
      "Pos": [
        208.77510063513182,
        1289.0000312443008
      ]
    },
    {
      "ID": "135711",
      "Pos": [
        178.27510063699447,
        1289.0000312443008
      ]
    },
    {
      "ID": "135710",
      "Pos": [
        164.19283269322477,
        1099.5050287157646
      ]
    },
    {
      "ID": "13570F",
      "Pos": [
        114.19283269322477,
        1099.5050287157646
      ]
    },
    {
      "ID": "13570E",
      "Pos": [
        189.19283269299194,
        1100.0050287158228
      ]
    },
    {
      "ID": "13570D",
      "Pos": [
        139.19283269322477,
        1099.5050287157646
      ]
    },
    {
      "ID": "13570C",
      "Pos": [
        89.192832693224773,
        1099.5050287157646
      ]
    },
    {
      "ID": "13570B",
      "Pos": [
        80.192832692991942,
        1100.0050287158228
      ]
    },
    {
      "ID": "13570A",
      "Pos": [
        117.47378624347039,
        367.50003124424256
      ]
    },
    {
      "ID": "135709",
      "Pos": [
        144.79774718917906,
        1623.0000305902213
      ]
    },
    {
      "ID": "135708",
      "Pos": [
        327.0329479414504,
        940.00003124424256
      ]
    },
    {
      "ID": "135707",
      "Pos": [
        219.0329479414504,
        940.00003124424256
      ]
    },
    {
      "ID": "135706",
      "Pos": [
        331.28333576116711,
        734.50003124424256
      ]
    },
    {
      "ID": "135705",
      "Pos": [
        259.28333576116711,
        734.50003124424256
      ]
    },
    {
      "ID": "135704",
      "Pos": [
        299.74521886650473,
        180.00003124424256
      ]
    },
    {
      "ID": "135703",
      "Pos": [
        205.28333576116711,
        734.50003124424256
      ]
    },
    {
      "ID": "135702",
      "Pos": [
        313.28333576116711,
        734.50003124424256
      ]
    },
    {
      "ID": "135701",
      "Pos": [
        72.797747189179063,
        1626.0000312443008
      ]
    },
    {
      "ID": "135700",
      "Pos": [
        71.283335761167109,
        757.00003124430077
      ]
    },
    {
      "ID": "1356A3",
      "Pos": [
        550.5,
        120.50003124447539
      ]
    },
    {
      "ID": "1356A1",
      "Pos": [
        34.999995500314981,
        1930.0711194318719
      ]
    },
    {
      "ID": "1356A0",
      "Pos": [
        40.5,
        120.50003124447539
      ]
    },
    {
      "ID": "13569A",
      "Pos": [
        25.781288280151784,
        13.974779365409631
      ]
    },
    {
      "ID": "135698",
      "Pos": [
        133.0,
        2180.0
      ]
    }
  ]
}