{
  "input": {
    "PanelType": "安装板",
    "PanelSize": [
      600.0,
      800.0
    ],
    "Parts": [
      {
        "ID": "ABAB",
        "Type": "零排",
        "Size": [
          25.0,
          157.0
        ]
      },
      {
        "ID": "ABAA",
        "Type": "地排",
        "Size": [
          25.0,
          160.0
        ]
      },
      {
        "ID": "92C5",
        "Type": "端子堵头",
        "Size": [
          9.0,
          42.0
        ]
      },
      {
        "ID": "9298",
        "Type": "端子堵头",
        "Size": [
          9.0,
          42.0
        ]
      },
      {
        "ID": "9297",
        "Type": "熔断器",
        "Size": [
          18.0,
          82.0
        ]
      },
      {
        "ID": "9296",
        "Type": "熔断器",
        "Size": [
          18.0,
          82.0
        ]
      },
      {
        "ID": "9295",
        "Type": "熔断器",
        "Size": [
          18.0,
          82.0
        ]
      },
      {
        "ID": "9294",
        "Type": "熔断器",
        "Size": [
          18.0,
          82.0
        ]
      },
      {
        "ID": "9293",
        "Type": "熔断器",
        "Size": [
          18.0,
          82.0
        ]
      },
      {
        "ID": "9292",
        "Type": "端子堵头",
        "Size": [
          9.0,
          42.0
        ]
      },
      {
        "ID": "9291",
        "Type": "熔断器",
        "Size": [
          18.0,
          82.0
        ]
      },
      {
        "ID": "9251",
        "Type": "端子堵头",
        "Size": [
          9.0,
          42.0
        ]
      },
      {
        "ID": "9250",
        "Type": "端子堵头",
        "Size": [
          9.0,
          42.0
        ]
      },
      {
        "ID": "924F",
        "Type": "端子堵头",
        "Size": [
          9.0,
          42.0
        ]
      },
      {
        "ID": "924E",
        "Type": "熔断器",
        "Size": [
          18.0,
          82.0
        ]
      },
      {
        "ID": "924D",
        "Type": "熔断器",
        "Size": [
          18.0,
          82.0
        ]
      },
      {
        "ID": "924C",
        "Type": "熔断器",
        "Size": [
          18.0,
          82.0
        ]
      },
      {
        "ID": "924B",
        "Type": "熔断器",
        "Size": [
          18.0,
          82.0
        ]
      },
      {
        "ID": "924A",
        "Type": "端子堵头",
        "Size": [
          9.0,
          42.0
        ]
      },
      {
        "ID": "9249",
        "Type": "接线端子",
        "Size": [
          43.0,
          149.01245176544762
        ]
      },
      {
        "ID": "9248",
        "Type": "微型断路器",
        "Size": [
          54.0,
          135.0
        ]
      },
      {
        "ID": "9247",
        "Type": "接线端子",
        "Size": [
          43.0,
          149.01245176544762
        ]
      },
      {
        "ID": "9246",
        "Type": "双电源自动转换开关",
        "Size": [
          245.0000005904585,
          258.00000589764386
        ]
      },
      {
        "ID": "9245",
        "Type": "微型断路器",
        "Size": [
          54.0,
          135.0
        ]
      },
      {
        "ID": "9244",
        "Type": "微型断路器",
        "Size": [
          18.0,
          135.0
        ]
      },
      {
        "ID": "9243",
        "Type": "微型断路器",
        "Size": [
          18.0,
          135.0
        ]
      },
      {
        "ID": "9242",
        "Type": "微型断路器",
        "Size": [
          18.0,
          135.0
        ]
      },
      {
        "ID": "9241",
        "Type": "微型断路器",
        "Size": [
          18.0,
          135.0
        ]
      },
      {
        "ID": "9240",
        "Type": "微型断路器",
        "Size": [
          18.0,
          135.0
        ]
      },
      {
        "ID": "923F",
        "Type": "微型断路器",
        "Size": [
          18.0,
          135.0
        ]
      },
      {
        "ID": "923E",
        "Type": "微型断路器",
        "Size": [
          18.0,
          135.0
        ]
      },
      {
        "ID": "923D",
        "Type": "微型断路器",
        "Size": [
          18.0,
          135.0
        ]
      },
      {
        "ID": "923C",
        "Type": "微型断路器",
        "Size": [
          18.0,
          135.0
        ]
      },
      {
        "ID": "923B",
        "Type": "电源监控",
        "Size": [
          136.0,
          111.11832940974273
        ]
      }
    ]
  },
  "output": [
    {
      "ID": "ABAB",
      "Pos": [
        516.6476604997879,
        496.3439591008064
      ]
    },
    {
      "ID": "ABAA",
      "Pos": [
        54.54729711776599,
        522.5835627212364
      ]
    },
    {
      "ID": "92C5",
      "Pos": [
        116.00000000011642,
        622.0000000014115
      ]
    },
    {
      "ID": "9298",
      "Pos": [
        233.00000000011642,
        124.5000000018772
      ]
    },
    {
      "ID": "9297",
      "Pos": [
        215.0,
        105.50000000186265
      ]
    },
    {
      "ID": "9296",
      "Pos": [
        197.0,
        105.50000000186265
      ]
    },
    {
      "ID": "9295",
      "Pos": [
        179.0,
        105.50000000186265
      ]
    },
    {
      "ID": "9294",
      "Pos": [
        161.0,
        105.50000000186265
      ]
    },
    {
      "ID": "9293",
      "Pos": [
        143.0,
        105.50000000186265
      ]
    },
    {
      "ID": "9292",
      "Pos": [
        116.00000000011642,
        124.5000000018772
      ]
    },
    {
      "ID": "9291",
      "Pos": [
        125.0,
        105.50000000186265
      ]
    },
    {
      "ID": "9251",
      "Pos": [
        285.0000000001164,
        622.0000000014115
      ]
    },
    {
      "ID": "9250",
      "Pos": [
        261.0000000001164,
        622.0000000014115
      ]
    },
    {
      "ID": "924F",
      "Pos": [
        197.00000000011642,
        307.00000000225555
      ]
    },
    {
      "ID": "924E",
      "Pos": [
        179.0,
        288.0000000022701
      ]
    },
    {
      "ID": "924D",
      "Pos": [
        161.0,
        288.0000000022701
      ]
    },
    {
      "ID": "924C",
      "Pos": [
        143.0,
        288.0000000022701
      ]
    },
    {
      "ID": "924B",
      "Pos": [
        125.0,
        288.0000000022701
      ]
    },
    {
      "ID": "924A",
      "Pos": [
        116.00000000011642,
        307.00000000225555
      ]
    },
    {
      "ID": "9249",
      "Pos": [
        441.0000000001164,
        65.98754823688068
      ]
    },
    {
      "ID": "9248",
      "Pos": [
        387.00000000023283,
        78.0000000023283
      ]
    },
    {
      "ID": "9247",
      "Pos": [
        344.0000000001164,
        65.98754823688068
      ]
    },
    {
      "ID": "9246",
      "Pos": [
        239.00000628223643,
        256.9999941064307
      ]
    },
    {
      "ID": "9245",
      "Pos": [
        290.00000000023283,
        78.0000000023283
      ]
    },
    {
      "ID": "9244",
      "Pos": [
        438.0,
        575.500000001397
      ]
    },
    {
      "ID": "9243",
      "Pos": [
        420.0,
        575.500000001397
      ]
    },
    {
      "ID": "9242",
      "Pos": [
        402.0,
        575.500000001397
      ]
    },
    {
      "ID": "9241",
      "Pos": [
        384.0,
        575.500000001397
      ]
    },
    {
      "ID": "9240",
      "Pos": [
        366.0,
        575.500000001397
      ]
    },
    {
      "ID": "923F",
      "Pos": [
        348.0,
        575.500000001397
      ]
    },
    {
      "ID": "923E",
      "Pos": [
        330.0,
        575.500000001397
      ]
    },
    {
      "ID": "923D",
      "Pos": [
        312.0,
        575.500000001397
      ]
    },
    {
      "ID": "923C",
      "Pos": [
        294.0,
        575.500000001397
      ]
    },
    {
      "ID": "923B",
      "Pos": [
        125.0,
        585.8816705916543
      ]
    }
  ]
}