{
  "input": {
    "PanelType": "安装板",
    "PanelSize": [
      700.0,
      1300.0
    ],
    "Parts": [
      {
        "ID": "120E2",
        "Type": "塑壳断路器",
        "Size": [
          92.0,
          150.0
        ]
      },
      {
        "ID": "120E1",
        "Type": "塑壳断路器",
        "Size": [
          92.0,
          150.0
        ]
      },
      {
        "ID": "120E0",
        "Type": "电源监控",
        "Size": [
          108.00000000046566,
          94.24295454472303
        ]
      },
      {
        "ID": "120DF",
        "Type": "双电源自动转换开关",
        "Size": [
          293.0,
          192.0
        ]
      },
      {
        "ID": "120DE",
        "Type": "微型断路器",
        "Size": [
          36.0,
          85.0
        ]
      },
      {
        "ID": "120DD",
        "Type": "微型断路器",
        "Size": [
          36.0,
          85.0
        ]
      },
      {
        "ID": "120DC",
        "Type": "微型断路器",
        "Size": [
          36.0,
          85.0
        ]
      },
      {
        "ID": "120DB",
        "Type": "微型断路器",
        "Size": [
          36.0,
          85.0
        ]
      },
      {
        "ID": "120DA",
        "Type": "微型断路器",
        "Size": [
          36.0,
          85.0
        ]
      },
      {
        "ID": "120D9",
        "Type": "微型断路器",
        "Size": [
          36.0,
          85.0
        ]
      },
      {
        "ID": "120D8",
        "Type": "微型断路器",
        "Size": [
          36.0,
          85.0
        ]
      },
      {
        "ID": "120D7",
        "Type": "微型断路器",
        "Size": [
          36.0,
          85.0
        ]
      },
      {
        "ID": "120D6",
        "Type": "微型断路器",
        "Size": [
          36.0,
          85.0
        ]
      },
      {
        "ID": "120D5",
        "Type": "微型断路器",
        "Size": [
          36.0,
          85.0
        ]
      },
      {
        "ID": "120D4",
        "Type": "微型断路器",
        "Size": [
          36.0,
          85.0
        ]
      },
      {
        "ID": "120D3",
        "Type": "微型断路器",
        "Size": [
          36.0,
          85.0
        ]
      },
      {
        "ID": "120D2",
        "Type": "微型断路器",
        "Size": [
          36.0,
          85.0
        ]
      },
      {
        "ID": "120D1",
        "Type": "微型断路器",
        "Size": [
          36.0,
          85.0
        ]
      },
      {
        "ID": "120D0",
        "Type": "微型断路器",
        "Size": [
          36.0,
          85.0
        ]
      },
      {
        "ID": "120CF",
        "Type": "微型断路器",
        "Size": [
          36.0,
          85.0
        ]
      },
      {
        "ID": "120CE",
        "Type": "微型断路器",
        "Size": [
          36.0,
          85.0
        ]
      },
      {
        "ID": "120CD",
        "Type": "微型断路器",
        "Size": [
          36.0,
          85.0
        ]
      },
      {
        "ID": "120CC",
        "Type": "微型断路器",
        "Size": [
          117.0,
          97.0
        ]
      },
      {
        "ID": "120CB",
        "Type": "微型断路器",
        "Size": [
          18.0,
          83.0
        ]
      },
      {
        "ID": "120CA",
        "Type": "塑壳断路器",
        "Size": [
          92.0,
          150.0
        ]
      },
      {
        "ID": "120C9",
        "Type": "智能照明控制模块",
        "Size": [
          216.0,
          104.0
        ]
      },
      {
        "ID": "120C8",
        "Type": "电流互感器",
        "Size": [
          125.0,
          30.0
        ]
      }
    ]
  },
  "output": [
    {
      "ID": "120E2",
      "Pos": [
        194.0,
        150.0
      ]
    },
    {
      "ID": "120E1",
      "Pos": [
        296.0,
        150.0
      ]
    },
    {
      "ID": "120E0",
      "Pos": [
        398.0,
        152.5
      ]
    },
    {
      "ID": "120DF",
      "Pos": [
        203.5,
        421.0
      ]
    },
    {
      "ID": "120DE",
      "Pos": [
        80.0,
        759.5
      ]
    },
    {
      "ID": "120DD",
      "Pos": [
        116.0,
        759.5
      ]
    },
    {
      "ID": "120DC",
      "Pos": [
        152.0,
        759.5
      ]
    },
    {
      "ID": "120DB",
      "Pos": [
        188.0,
        759.5
      ]
    },
    {
      "ID": "120DA",
      "Pos": [
        224.0,
        759.5
      ]
    },
    {
      "ID": "120D9",
      "Pos": [
        260.0,
        759.5
      ]
    },
    {
      "ID": "120D8",
      "Pos": [
        296.0,
        759.5
      ]
    },
    {
      "ID": "120D7",
      "Pos": [
        332.0,
        759.5
      ]
    },
    {
      "ID": "120D6",
      "Pos": [
        368.0,
        759.5
      ]
    },
    {
      "ID": "120D5",
      "Pos": [
        404.0,
        759.5
      ]
    },
    {
      "ID": "120D4",
      "Pos": [
        440.0,
        759.5
      ]
    },
    {
      "ID": "120D3",
      "Pos": [
        476.0,
        759.5
      ]
    },
    {
      "ID": "120D2",
      "Pos": [
        512.0,
        759.5
      ]
    },
    {
      "ID": "120D1",
      "Pos": [
        548.0,
        759.5
      ]
    },
    {
      "ID": "120D0",
      "Pos": [
        584.0,
        759.5
      ]
    },
    {
      "ID": "120CF",
      "Pos": [
        64.5,
        944.0
      ]
    },
    {
      "ID": "120CE",
      "Pos": [
        100.5,
        944.0
      ]
    },
    {
      "ID": "120CD",
      "Pos": [
        136.5,
        944.0
      ]
    },
    {
      "ID": "120CC",
      "Pos": [
        172.5,
        944.0
      ]
    },
    {
      "ID": "120CB",
      "Pos": [
        289.5,
        944.0
      ]
    },
    {
      "ID": "120CA",
      "Pos": [
        317.5,
        944.0
      ]
    },
    {
      "ID": "120C9",
      "Pos": [
        419.5,
        944.0
      ]
    },
    {
      "ID": "120C8",
      "Pos": [
        337.0,
        634.5
      ]
    }
  ]
}