{
  "cabinets": [
    {
      "order": 1,
      "cabinet_name": "2024030507北京市房山区阎村镇04街区项目体育用房项目-第二批非标_819b9fd6",
      "cabinet_use": "配电柜",
      "cabinet_model": "",
      "wiring_method": "",
      "cabinet_width": 800,
      "cabinet_height": 2000,
      "panels": [
        {
          "order": 1,
          "panel_type": "默认面板",
          "operation_method": "",
          "panel_width": 800,
          "panel_height": 2000,
          "parts": [
            {
              "order": 1,
              "part_type": "时间继电器",
              "part_model": "",
              "part_width": 30,
              "part_height": 71,
              "part_id": "135B0B"
            },
            {
              "order": 2,
              "part_type": "端子堵头",
              "part_model": "",
              "part_width": 9,
              "part_height": 42,
              "part_id": "135B0A"
            },
            {
              "order": 3,
              "part_type": "端子堵头",
              "part_model": "",
              "part_width": 9,
              "part_height": 42,
              "part_id": "135B09"
            },
            {
              "order": 4,
              "part_type": "熔断器",
              "part_model": "",
              "part_width": 18,
              "part_height": 82,
              "part_id": "135B08"
            },
            {
              "order": 5,
              "part_type": "时间继电器",
              "part_model": "",
              "part_width": 22,
              "part_height": 71,
              "part_id": "135B07"
            },
            {
              "order": 6,
              "part_type": "时间继电器",
              "part_model": "",
              "part_width": 22,
              "part_height": 71,
              "part_id": "135B06"
            },
            {
              "order": 7,
              "part_type": "时间继电器",
              "part_model": "",
              "part_width": 30,
              "part_height": 71,
              "part_id": "135B05"
            },
            {
              "order": 8,
              "part_type": "时间继电器",
              "part_model": "",
              "part_width": 30,
              "part_height": 71,
              "part_id": "135B04"
            },
            {
              "order": 9,
              "part_type": "控制与保护开关",
              "part_model": "",
              "part_width": 93,
              "part_height": 249,
              "part_id": "135B03"
            },
            {
              "order": 10,
              "part_type": "控制与保护开关",
              "part_model": "",
              "part_width": 93,
              "part_height": 249,
              "part_id": "135B02"
            },
            {
              "order": 11,
              "part_type": "控制与保护开关",
              "part_model": "",
              "part_width": 93,
              "part_height": 249,
              "part_id": "135B01"
            },
            {
              "order": 12,
              "part_type": "微型断路器",
              "part_model": "",
              "part_width": 54,
              "part_height": 135,
              "part_id": "135B00"
            },
            {
              "order": 13,
              "part_type": "微型断路器",
              "part_model": "",
              "part_width": 54,
              "part_height": 135,
              "part_id": "135AFF"
            },
            {
              "order": 14,
              "part_type": "微型断路器",
              "part_model": "",
              "part_width": 54,
              "part_height": 135,
              "part_id": "135AFE"
            },
            {
              "order": 15,
              "part_type": "控制与保护开关",
              "part_model": "",
              "part_width": 93,
              "part_height": 249,
              "part_id": "135AFD"
            },
            {
              "order": 16,
              "part_type": "微型断路器",
              "part_model": "",
              "part_width": 54,
              "part_height": 135,
              "part_id": "135AFC"
            },
            {
              "order": 17,
              "part_type": "微型断路器",
              "part_model": "",
              "part_width": 57,
              "part_height": 40,
              "part_id": "135AFB"
            },
            {
              "order": 18,
              "part_type": "微型断路器",
              "part_model": "",
              "part_width": 105,
              "part_height": 55,
              "part_id": "135AFA"
            },
            {
              "order": 19,
              "part_type": "熔断器",
              "part_model": "",
              "part_width": 108,
              "part_height": 82,
              "part_id": "135AF9"
            },
            {
              "order": 20,
              "part_type": "接线端子",
              "part_model": "",
              "part_width": 24,
              "part_height": 43,
              "part_id": "135AF8"
            },
            {
              "order": 21,
              "part_type": "电能表",
              "part_model": "",
              "part_width": 72,
              "part_height": 90,
              "part_id": "135AF7"
            },
            {
              "order": 22,
              "part_type": "双电源自动转换开关",
              "part_model": "",
              "part_width": 265,
              "part_height": 272,
              "part_id": "135AF6"
            },
            {
              "order": 23,
              "part_type": "塑壳断路器",
              "part_model": "",
              "part_width": 93,
              "part_height": 155,
              "part_id": "135AF5"
            },
            {
              "order": 24,
              "part_type": "塑壳断路器",
              "part_model": "",
              "part_width": 93,
              "part_height": 155,
              "part_id": "135AF4"
            },
            {
              "order": 25,
              "part_type": "浪涌保护器",
              "part_model": "",
              "part_width": 144,
              "part_height": 135,
              "part_id": "135AF3"
            },
            {
              "order": 26,
              "part_type": "塑壳断路器",
              "part_model": "",
              "part_width": 93,
              "part_height": 155,
              "part_id": "135AF2"
            },
            {
              "order": 27,
              "part_type": "塑壳断路器",
              "part_model": "",
              "part_width": 125,
              "part_height": 150,
              "part_id": "135AF1"
            },
            {
              "order": 28,
              "part_type": "微型断路器",
              "part_model": "",
              "part_width": 63,
              "part_height": 146,
              "part_id": "135AF0"
            },
            {
              "order": 29,
              "part_type": "微型断路器",
              "part_model": "",
              "part_width": 63,
              "part_height": 146,
              "part_id": "135AEF"
            },
            {
              "order": 30,
              "part_type": "微型断路器",
              "part_model": "",
              "part_width": 63,
              "part_height": 146,
              "part_id": "135AEE"
            },
            {
              "order": 31,
              "part_type": "微型断路器",
              "part_model": "",
              "part_width": 54,
              "part_height": 135,
              "part_id": "135AED"
            },
            {
              "order": 32,
              "part_type": "微型断路器",
              "part_model": "",
              "part_width": 18,
              "part_height": 135,
              "part_id": "135AEC"
            },
            {
              "order": 33,
              "part_type": "微型断路器",
              "part_model": "",
              "part_width": 18,
              "part_height": 135,
              "part_id": "135AEB"
            },
            {
              "order": 34,
              "part_type": "微型断路器",
              "part_model": "",
              "part_width": 18,
              "part_height": 135,
              "part_id": "135AEA"
            },
            {
              "order": 35,
              "part_type": "浪涌保护器",
              "part_model": "",
              "part_width": 146,
              "part_height": 135,
              "part_id": "135AE9"
            },
            {
              "order": 36,
              "part_type": "时间继电器",
              "part_model": "",
              "part_width": 30,
              "part_height": 71,
              "part_id": "135AE8"
            },
            {
              "order": 37,
              "part_type": "接线端子",
              "part_model": "",
              "part_width": 25,
              "part_height": 43,
              "part_id": "135AE7"
            },
            {
              "order": 38,
              "part_type": "接线端子",
              "part_model": "",
              "part_width": 25,
              "part_height": 43,
              "part_id": "135AE6"
            },
            {
              "order": 39,
              "part_type": "端子堵头",
              "part_model": "",
              "part_width": 9,
              "part_height": 42,
              "part_id": "135AE5"
            },
            {
              "order": 40,
              "part_type": "接线端子",
              "part_model": "",
              "part_width": 25,
              "part_height": 43,
              "part_id": "135AE4"
            },
            {
              "order": 41,
              "part_type": "接线端子",
              "part_model": "",
              "part_width": 25,
              "part_height": 43,
              "part_id": "135AE3"
            },
            {
              "order": 42,
              "part_type": "端子堵头",
              "part_model": "",
              "part_width": 9,
              "part_height": 42,
              "part_id": "135AE2"
            },
            {
              "order": 43,
              "part_type": "熔断器",
              "part_model": "",
              "part_width": 18,
              "part_height": 82,
              "part_id": "135AE1"
            },
            {
              "order": 44,
              "part_type": "时间继电器",
              "part_model": "",
              "part_width": 22,
              "part_height": 71,
              "part_id": "135AE0"
            },
            {
              "order": 45,
              "part_type": "时间继电器",
              "part_model": "",
              "part_width": 22,
              "part_height": 71,
              "part_id": "135ADF"
            },
            {
              "order": 46,
              "part_type": "时间继电器",
              "part_model": "",
              "part_width": 30,
              "part_height": 71,
              "part_id": "135ADE"
            },
            {
              "order": 47,
              "part_type": "时间继电器",
              "part_model": "",
              "part_width": 30,
              "part_height": 71,
              "part_id": "135ADD"
            },
            {
              "order": 48,
              "part_type": "接线端子",
              "part_model": "",
              "part_width": 25,
              "part_height": 43,
              "part_id": "135ADC"
            },
            {
              "order": 49,
              "part_type": "接线端子",
              "part_model": "",
              "part_width": 25,
              "part_height": 43,
              "part_id": "135ADB"
            },
            {
              "order": 50,
              "part_type": "端子堵头",
              "part_model": "",
              "part_width": 9,
              "part_height": 42,
              "part_id": "135ADA"
            },
            {
              "order": 51,
              "part_type": "接线端子",
              "part_model": "",
              "part_width": 25,
              "part_height": 43,
              "part_id": "135AD9"
            },
            {
              "order": 52,
              "part_type": "接线端子",
              "part_model": "",
              "part_width": 25,
              "part_height": 43,
              "part_id": "135AD8"
            },
            {
              "order": 53,
              "part_type": "端子堵头",
              "part_model": "",
              "part_width": 9,
              "part_height": 42,
              "part_id": "135AD7"
            },
            {
              "order": 54,
              "part_type": "时间继电器",
              "part_model": "",
              "part_width": 30,
              "part_height": 71,
              "part_id": "135AD6"
            },
            {
              "order": 55,
              "part_type": "接线端子",
              "part_model": "",
              "part_width": 25,
              "part_height": 43,
              "part_id": "135AD5"
            },
            {
              "order": 56,
              "part_type": "接线端子",
              "part_model": "",
              "part_width": 25,
              "part_height": 43,
              "part_id": "135AD4"
            },
            {
              "order": 57,
              "part_type": "端子堵头",
              "part_model": "",
              "part_width": 9,
              "part_height": 42,
              "part_id": "135AD3"
            },
            {
              "order": 58,
              "part_type": "接线端子",
              "part_model": "",
              "part_width": 25,
              "part_height": 43,
              "part_id": "135AD2"
            },
            {
              "order": 59,
              "part_type": "接线端子",
              "part_model": "",
              "part_width": 25,
              "part_height": 43,
              "part_id": "135AD1"
            },
            {
              "order": 60,
              "part_type": "端子堵头",
              "part_model": "",
              "part_width": 9,
              "part_height": 42,
              "part_id": "135AD0"
            },
            {
              "order": 61,
              "part_type": "端子堵头",
              "part_model": "",
              "part_width": 9,
              "part_height": 42,
              "part_id": "135ACF"
            },
            {
              "order": 62,
              "part_type": "端子堵头",
              "part_model": "",
              "part_width": 9,
              "part_height": 42,
              "part_id": "135ACE"
            },
            {
              "order": 63,
              "part_type": "熔断器",
              "part_model": "",
              "part_width": 18,
              "part_height": 82,
              "part_id": "135ACD"
            },
            {
              "order": 64,
              "part_type": "时间继电器",
              "part_model": "",
              "part_width": 22,
              "part_height": 71,
              "part_id": "135ACC"
            },
            {
              "order": 65,
              "part_type": "时间继电器",
              "part_model": "",
              "part_width": 22,
              "part_height": 71,
              "part_id": "135ACB"
            },
            {
              "order": 66,
              "part_type": "时间继电器",
              "part_model": "",
              "part_width": 30,
              "part_height": 71,
              "part_id": "135ACA"
            },
            {
              "order": 67,
              "part_type": "时间继电器",
              "part_model": "",
              "part_width": 30,
              "part_height": 71,
              "part_id": "135AC9"
            },
            {
              "order": 68,
              "part_type": "时间继电器",
              "part_model": "",
              "part_width": 30,
              "part_height": 71,
              "part_id": "135AC8"
            },
            {
              "order": 69,
              "part_type": "接线端子",
              "part_model": "",
              "part_width": 25,
              "part_height": 43,
              "part_id": "135AC7"
            },
            {
              "order": 70,
              "part_type": "接线端子",
              "part_model": "",
              "part_width": 25,
              "part_height": 43,
              "part_id": "135AC6"
            },
            {
              "order": 71,
              "part_type": "端子堵头",
              "part_model": "",
              "part_width": 9,
              "part_height": 42,
              "part_id": "135AC5"
            },
            {
              "order": 72,
              "part_type": "接线端子",
              "part_model": "",
              "part_width": 25,
              "part_height": 43,
              "part_id": "135AC4"
            },
            {
              "order": 73,
              "part_type": "接线端子",
              "part_model": "",
              "part_width": 25,
              "part_height": 43,
              "part_id": "135AC3"
            },
            {
              "order": 74,
              "part_type": "端子堵头",
              "part_model": "",
              "part_width": 9,
              "part_height": 42,
              "part_id": "135AC2"
            },
            {
              "order": 75,
              "part_type": "端子堵头",
              "part_model": "",
              "part_width": 9,
              "part_height": 42,
              "part_id": "135AC1"
            },
            {
              "order": 76,
              "part_type": "端子堵头",
              "part_model": "",
              "part_width": 9,
              "part_height": 42,
              "part_id": "135AC0"
            },
            {
              "order": 77,
              "part_type": "熔断器",
              "part_model": "",
              "part_width": 18,
              "part_height": 82,
              "part_id": "135ABF"
            },
            {
              "order": 78,
              "part_type": "时间继电器",
              "part_model": "",
              "part_width": 22,
              "part_height": 71,
              "part_id": "135ABE"
            },
            {
              "order": 79,
              "part_type": "时间继电器",
              "part_model": "",
              "part_width": 22,
              "part_height": 71,
              "part_id": "135ABD"
            },
            {
              "order": 80,
              "part_type": "时间继电器",
              "part_model": "",
              "part_width": 30,
              "part_height": 71,
              "part_id": "135ABC"
            },
            {
              "order": 81,
              "part_type": "时间继电器",
              "part_model": "",
              "part_width": 30,
              "part_height": 71,
              "part_id": "135ABB"
            },
            {
              "order": 82,
              "part_type": "地排",
              "part_model": "",
              "part_width": 730,
              "part_height": 179,
              "part_id": "135A7F"
            }
          ],
          "panel_id": "63dc059d-d953-4ebc-82d4-483b898657c6"
        }
      ],
      "cabinet_id": "f9db5139-8a8d-48c5-aa8f-4aecde99fc20"
    }
  ]
}
