{
  "input": {
    "PanelType": "安装板",
    "PanelSize": [
      700.0,
      1300.0
    ],
    "Parts": [
      {
        "ID": "15211",
        "Type": "塑壳断路器",
        "Size": [
          92.00000999998883,
          150.0
        ]
      },
      {
        "ID": "15210",
        "Type": "塑壳断路器",
        "Size": [
          92.00000999998883,
          150.0
        ]
      },
      {
        "ID": "1520F",
        "Type": "塑壳断路器",
        "Size": [
          92.00000999998883,
          150.0
        ]
      },
      {
        "ID": "1520E",
        "Type": "塑壳断路器",
        "Size": [
          92.00000999998883,
          150.0
        ]
      },
      {
        "ID": "1520D",
        "Type": "电流互感器",
        "Size": [
          60.5,
          33.0
        ]
      },
      {
        "ID": "1520C",
        "Type": "电流互感器",
        "Size": [
          60.5,
          33.0
        ]
      },
      {
        "ID": "1520B",
        "Type": "电流互感器",
        "Size": [
          60.5,
          33.0
        ]
      },
      {
        "ID": "1520A",
        "Type": "塑壳断路器",
        "Size": [
          92.00000999998883,
          150.0
        ]
      },
      {
        "ID": "15209",
        "Type": "接线端子",
        "Size": [
          115.49999999962165,
          75.0
        ]
      },
      {
        "ID": "15208",
        "Type": "电源监控",
        "Size": [
          91.34090180881321,
          99.5458718072623
        ]
      },
      {
        "ID": "15207",
        "Type": "塑壳断路器",
        "Size": [
          92.00000999998883,
          150.0
        ]
      },
      {
        "ID": "15206",
        "Type": "隔离开关",
        "Size": [
          142.05411877809092,
          135.0
        ]
      },
      {
        "ID": "15205",
        "Type": "隔离开关",
        "Size": [
          142.05411877809092,
          135.0
        ]
      },
      {
        "ID": "15204",
        "Type": "双电源自动转换开关",
        "Size": [
          289.0,
          136.0
        ]
      }
    ]
  },
  "output": [
    {
      "ID": "15211",
      "Pos": [
        557.4389649704681,
        949.1465919203765
      ]
    },
    {
      "ID": "15210",
      "Pos": [
        457.8394689388806,
        949.1465919203765
      ]
    },
    {
      "ID": "1520F",
      "Pos": [
        355.06355982169043,
        949.1465919203765
      ]
    },
    {
      "ID": "1520E",
      "Pos": [
        255.27653204964008,
        949.1465919203765
      ]
    },
    {
      "ID": "1520D",
      "Pos": [
        113.21430723241065,
        678.6978941940761
      ]
    },
    {
      "ID": "1520C",
      "Pos": [
        144.29998872056603,
        720.9451846921293
      ]
    },
    {
      "ID": "1520B",
      "Pos": [
        83.79998872056603,
        720.9451846921293
      ]
    },
    {
      "ID": "1520A",
      "Pos": [
        47.72824962192681,
        949.1465919203765
      ]
    },
    {
      "ID": "15209",
      "Pos": [
        372.9593289340264,
        543.1305440347351
      ]
    },
    {
      "ID": "15208",
      "Pos": [
        490.8909487465862,
        533.4026178675704
      ]
    },
    {
      "ID": "15207",
      "Pos": [
        150.86210086301435,
        949.1465919203765
      ]
    },
    {
      "ID": "15206",
      "Pos": [
        287.0509585114778,
        255.49821219121804
      ]
    },
    {
      "ID": "15205",
      "Pos": [
        67.30033862480195,
        255.49821219121804
      ]
    },
    {
      "ID": "15204",
      "Pos": [
        65.98092267598258,
        519.0724165411957
      ]
    }
  ]
}